box0/__init__.py
box0/_binding.py
box0/device.py
box0/exceptions.py
box0/extra.py
box0/generic.py
box0/backend/__init__.py
box0/backend/usb.py
box0/driver/__init__.py
box0/driver/ads1220.py
box0/driver/adxl345.py
box0/driver/bmp180.py
box0/driver/driver.py
box0/driver/hbridge.py
box0/driver/mcp342x.py
box0/misc/__init__.py
box0/misc/box0v5/__init__.py
box0/misc/box0v5/ps.py
box0/module/__init__.py
box0/module/ain.py
box0/module/aout.py
box0/module/dio.py
box0/module/i2c.py
box0/module/module.py
box0/module/pwm.py
box0/module/spi.py
box0-0.3.1.dist-info/COPYING
box0-0.3.1.dist-info/METADATA
box0-0.3.1.dist-info/WHEEL
box0-0.3.1.dist-info/top_level.txt
box0-0.3.1.dist-info/RECORD
