Metadata-Version: 2.1
Name: box0
Version: 0.3.1
Summary: libbox0 Binding
Home-page: https://www.madresistor.com/box0
Author: Kuldeep Singh Dhaka
Author-email: kuldeep@madresistor.com
License: GPLv3+
Keywords: box0 libbox0 daq
Platform: UNKNOWN
Classifier: Development Status :: 3 - Alpha
Classifier: License :: OSI Approved :: GNU General Public License v3 or later (GPLv3+)
Classifier: Topic :: Scientific/Engineering
Requires-Dist: cffi (>=1.0.0)
Requires-Dist: numpy (>=1.11.0)
